{
  "id": "evt-26031582",
  "name": "Essential In-Person | Denver, CO",
  "title": "Essential In-Person | Denver, CO",
  "city": "Denver",
  "state": "CO",
  "instructor": "Ryan Lystad",
  "enrolledStudents": 1,
  "instrumentsPurchased": 1,
  "capacity": 25,
  "minViableEnrollment": 8,
  "type": "Essential",
  "mode": "In-Person",
  "status": "upcoming",
  "featuredImage": "https://picsum.photos/seed/evt-26031582/800/400",
  "date": "2025-11-22T08:00:00-06:00",
  "startDate": "2025-11-22T08:00:00-06:00",
  "endDate": "2025-11-22T18:00:00-06:00",
  "location": {
    "city": "Denver",
    "state": "CO"
  },
  "enrolledCount": 1,
  "learndashGroup": "26031582",
  "venue": {
    "name": "",
    "address": "3333 Regis Boulevard",
    "address2": "Peter Claver Hall Room 409",
    "city": "Denver",
    "state": "CO",
    "zipcode": "80221",
    "fullAddress": "3333 Regis Boulevard Peter Claver Hall Room 409 Denver, CO 80221"
  },
  "schedule": {
    "day1": {
      "startTime": "8:00 AM",
      "endTime": "6:00 PM"
    },
    "day2": {
      "startTime": "8:00 AM",
      "endTime": "6:00 PM"
    }
  },
  "headline": "Essential Hybrid Training, which includes an online pre-course/intro.",
  "evaluationForm": "Denver, CO-2025-11-22: Ryan Lystad"
}